{"type":"FeatureCollection", "features": [
{"type":"Feature","geometry":{"type":"MultiLineString","coordinates":[[[7.114842,43.869585],[7.114869872212914,43.869663386538186]],[[7.114884538262421,43.86970463266576],[7.114962754998484,43.86992460584072]],[[7.116177474731558,43.872686565162766],[7.117073,43.873978]]]},"properties":{"Id":653,"NIV1_14":3,"LIB1_14":"FORETS ET MILIEUX SEMI-NATURELS","NIV2_14":31,"LIB2_14":"Forets","NIV3_14":313,"LIB3_14":"Forets melangees","Area_m2":7415680.6201,"Area_ha":741.568062,"Donnee_exo":"BD FORET IFN - Images Landsat 8","DOUTE_14":"Non"}},
{"type":"Feature","geometry":{"type":"MultiLineString","coordinates":[[[7.114869872212914,43.869663386538186],[7.114884538262421,43.86970463266576]],[[7.114962754998484,43.86992460584072],[7.115055484710277,43.87018539464557]]]},"properties":{"Id":139044,"NIV1_14":3,"LIB1_14":"FORETS ET MILIEUX SEMI-NATURELS","NIV2_14":32,"LIB2_14":"Milieux a vegetation arbustive et ou herbacee","NIV3_14":324,"LIB3_14":"Foret et vegetation arbustive en mutation","Area_m2":35220.0669,"Area_ha":3.5220067,"Donnee_exo":"BD FORET IFN - Images Landsat 8","DOUTE_14":"Non"}},
{"type":"Feature","geometry":{"type":"MultiLineString","coordinates":[[[7.115055484710277,43.87018539464557],[7.115401680618402,43.8711590202007]],[[7.115906613558815,43.872295956916574],[7.116177474731558,43.872686565162766]]]},"properties":{"Id":139040,"NIV1_14":3,"LIB1_14":"FORETS ET MILIEUX SEMI-NATURELS","NIV2_14":31,"LIB2_14":"Forets","NIV3_14":311,"LIB3_14":"Forets de feuillus","Area_m2":70800.4702,"Area_ha":7.080047,"Donnee_exo":"BD FORET IFN - Images Landsat 8","DOUTE_14":"Non"}},
{"type":"Feature","geometry":{"type":"LineString","coordinates":[[7.115401680618402,43.8711590202007],[7.1157,43.871998],[7.115906613558815,43.872295956916574]]},"properties":{"Id":139042,"NIV1_14":3,"LIB1_14":"FORETS ET MILIEUX SEMI-NATURELS","NIV2_14":32,"LIB2_14":"Milieux a vegetation arbustive et ou herbacee","NIV3_14":324,"LIB3_14":"Foret et vegetation arbustive en mutation","Area_m2":23285.29,"Area_ha":2.328529,"Donnee_exo":"BD FORET IFN - Images Landsat 8","DOUTE_14":"Non"}}
]}